MANIFEST.in
README.rst
requirements.txt
setup.py
bin/url-shortener
url_shortener/__init__.py
url_shortener/config.py
url_shortener/shorten.py
url_shortener.egg-info/PKG-INFO
url_shortener.egg-info/SOURCES.txt
url_shortener.egg-info/dependency_links.txt
url_shortener.egg-info/not-zip-safe
url_shortener.egg-info/requires.txt
url_shortener.egg-info/top_level.txt
url_shortener/static/stylesheets/bootstrap-responsive.css
url_shortener/static/stylesheets/bootstrap.css
url_shortener/templates/index.html
url_shortener/templates/invalid.html
url_shortener/templates/missing.html
url_shortener/templates/result.html
url_shortener/templates/layouts/default.html