Metadata-Version: 1.1
Name: url-shortener
Version: 0.5.16
Summary: Simple URL Shortener
Home-page: https://github.com/pyr/url-shortener
Author: Pierre-Yves Ritschard
Author-email: pyr@spootnik.org
License: MIT
Platform: UNKNOWN
Classifier: Development Status :: 5 - Production/Stable
Classifier: Intended Audience :: Developers
Classifier: License :: OSI Approved :: MIT License
Classifier: Natural Language :: English
Classifier: Programming Language :: Python
Classifier: Programming Language :: Python :: 3
